cosmic_shapes/gen_csh_gx_cat.pyx
cosmic_shapes/__init__.py
cosmic_shapes/setup.py
cosmic_shapes/python_helpers.py
cosmic_shapes/gen_csh_gx_cat.c
cosmic_shapes/gen_csh_gx_cat.so
cosmic_shapes/cython_helpers.so
cosmic_shapes/cosmic_shapes.so
cosmic_shapes/cosmic_shapes.c
cosmic_shapes/cython_helpers.pxd
cosmic_shapes/cosmic_shapes.pyx
cosmic_shapes/shape_analysis.py
cosmic_shapes/__init__.pxd
cosmic_shapes/cython_helpers.c
cosmic_shapes/cython_helpers.pyx
cosmic_shapes/get_hdf5.py
cosmic_shapes/__pycache__/shape_analysis.cpython-38.pyc
cosmic_shapes/__pycache__/__init__.cpython-38.pyc
cosmic_shapes/__pycache__/python_helpers.cpython-38.pyc
cosmic_shapes/__pycache__/get_hdf5.cpython-38.pyc
cosmic_shapes/for_docs/gen_csh_gx_cat.pyx
cosmic_shapes/for_docs/cython_helpers.pxd
cosmic_shapes/for_docs/cosmic_shapes.pyx
cosmic_shapes/for_docs/cython_helpers.pyx
cosmic_shapes-1.12.0.dist-info/METADATA
cosmic_shapes-1.12.0.dist-info/RECORD
cosmic_shapes-1.12.0.dist-info/top_level.txt
cosmic_shapes-1.12.0.dist-info/WHEEL
cosmic_shapes.libs/libomp-52546b9a.so
