Metadata-Version: 2.1
Name: cosmic-shapes
Version: 1.12.0
Summary: Implements various ellipsoidal shape identification algorithms for 3D particle data
Home-page: UNKNOWN
Author: Tibor Dome
Author-email: tibor.doeme@gmail.com
License: MIT
Project-URL: Documentation, https://cosmic-shapes.readthedocs.io/en/latest/
Project-URL: Source, https://github.com/tibordome/cosmic_shapes
Platform: UNKNOWN
Classifier: License :: OSI Approved :: MIT License
Classifier: Programming Language :: Python :: 3
Classifier: Programming Language :: Python :: 3.7
Requires-Dist: cython
Requires-Dist: numpy (>=1.19.2)
Requires-Dist: scikit-learn
Requires-Dist: mpi4py
Requires-Dist: h5py
Requires-Dist: matplotlib
Requires-Dist: pynbody
Requires-Dist: nbodykit
Requires-Dist: pynverse
